{
  "features": [
    {
      "geometry": {
        "type": "Point",
        "coordinates": [
          34.423131,
          30.87659
        ]
      },
      "type": "Feature",
      "id": "darmc-location-6808",
      "properties": {
        "snippet": "Unknown; 330 BC - AD 640",
        "link": "https://pleiades.stoa.org/places/687988/darmc-location-6808",
        "description": "500K scale point location",
        "location_precision": "precise",
        "title": "DARMC location 6808"
      }
    },
    {
      "geometry": {
        "type": "Point",
        "coordinates": [
          34.432417,
          30.87593
        ]
      },
      "type": "Feature",
      "id": "dare-location",
      "properties": {
        "snippet": "Settlement; 330 BC - AD 640",
        "link": "https://pleiades.stoa.org/places/687988/dare-location",
        "description": "Representative point location, site precision",
        "location_precision": "precise",
        "title": "DARE Location"
      }
    }
  ],
  "contributors": [
    {
      "username": null,
      "name": "R. Talbert"
    },
    {
      "username": "jahlfeldt",
      "homepage": null,
      "name": "Johan \u00c5hlfeldt",
      "uri": "https://pleiades.stoa.org/author/jahlfeldt"
    },
    {
      "username": "adamp",
      "homepage": null,
      "name": "Adam Prins",
      "uri": "https://pleiades.stoa.org/author/adamp"
    },
    {
      "username": null,
      "name": "Jen Thum"
    },
    {
      "username": "jbecker",
      "homepage": null,
      "name": "Jeffrey Becker",
      "uri": "https://pleiades.stoa.org/author/jbecker"
    },
    {
      "username": "thomase",
      "homepage": null,
      "name": "Tom Elliott",
      "uri": "https://pleiades.stoa.org/author/thomase"
    },
    {
      "username": null,
      "name": "DARMC"
    },
    {
      "username": null,
      "name": "Herbert Verreth"
    },
    {
      "username": "sgillies",
      "homepage": null,
      "name": "Sean Gillies",
      "uri": "https://pleiades.stoa.org/author/sgillies"
    },
    {
      "username": null,
      "name": "Mark Depauw"
    }
  ],
  "locations": [
    {
      "contributors": [
        {
          "username": null,
          "name": "DARMC, R. Talbert, T. Elliott, S. Gillies"
        }
      ],
      "associationCertainty": "certain",
      "attestations": [
        {
          "timePeriod": "hellenistic-republican",
          "timePeriodURI": "https://pleiades.stoa.org/vocabularies/time-periods/hellenistic-republican",
          "confidence": "confident",
          "confidenceURI": "https://pleiades.stoa.org/vocabularies/attestation-confidence/confident"
        },
        {
          "timePeriod": "roman",
          "timePeriodURI": "https://pleiades.stoa.org/vocabularies/time-periods/roman",
          "confidence": "confident",
          "confidenceURI": "https://pleiades.stoa.org/vocabularies/attestation-confidence/confident"
        },
        {
          "timePeriod": "late-antique",
          "timePeriodURI": "https://pleiades.stoa.org/vocabularies/time-periods/late-antique",
          "confidence": "confident",
          "confidenceURI": "https://pleiades.stoa.org/vocabularies/attestation-confidence/confident"
        }
      ],
      "references": [
        {
          "alternateURI": "",
          "accessURI": "https://darmc.harvard.edu/",
          "citationDetail": "6808",
          "citationTypeURI": "http://purl.org/spar/cito/citesAsDataSource",
          "shortTitle": "DARMC",
          "bibliographicURI": "https://www.zotero.org/groups/2533/pleiades/items/itemKey/9UD9W75C",
          "formattedCitation": "Michael McCormick, Giovanni Zambotti, Leland Grigoli, and Kelly Gibson, eds., The Digital Atlas of Roman and Medieval Civilizations (Cambridge (Massachusetts): Harvard University, 2007-), 6808.",
          "otherIdentifier": " ",
          "type": "citesAsDataSource"
        }
      ],
      "id": "darmc-location-6808",
      "featureTypeURI": [
        "https://pleiades.stoa.org/vocabularies/place-types/unknown"
      ],
      "end": 640,
      "title": "DARMC location 6808",
      "provenance": "DARMC OBJECTID: 6808",
      "associationCertaintyURI": "https://pleiades.stoa.org/vocabularies/association-certainty/certain",
      "start": -330,
      "locationTypeURI": [
        "https://pleiades.stoa.org/vocabularies/place-types/unknown"
      ],
      "archaeologicalRemains": "unknown",
      "details": "DARMC OBJECTID: 6808",
      "review_state": "published",
      "accuracy_value": 10.0,
      "accuracy": "https://pleiades.stoa.org/features/metadata/darmc-a",
      "featureType": [
        "unknown"
      ],
      "description": "500K scale point location",
      "created": "2011-03-09T19:34:42Z",
      "geometry": {
        "type": "Point",
        "coordinates": [
          34.423131,
          30.87659
        ]
      },
      "locationType": [
        "representative"
      ],
      "uri": "https://pleiades.stoa.org/places/687988/darmc-location-6808",
      "creators": [
        {
          "username": null,
          "name": "B. Isaac"
        }
      ],
      "@type": "Location",
      "history": [
        {
          "comment": "Global migration and reindexing of citations and provenance, February 2012",
          "modifiedBy": "admin",
          "modified": "2012-02-15T07:55:44Z"
        },
        {
          "action": "Publish externally",
          "modifiedBy": "thomase",
          "modified": "2011-03-10T04:59:48Z"
        },
        {
          "action": "Submit for review",
          "modifiedBy": "sgillies",
          "modified": "2011-03-09T19:34:43Z"
        },
        {
          "comment": "New locations, coordinates, and metadata from Harvard's DARMC project. See http://atlantides.org/trac/pleiades/wiki/PlaceUpgradesAndMigrations",
          "modifiedBy": "sgillies",
          "modified": "2011-03-09T19:34:43Z"
        },
        {
          "action": "Create",
          "modifiedBy": "sgillies",
          "modified": "2011-03-09T19:34:42Z"
        }
      ]
    },
    {
      "contributors": [],
      "associationCertainty": "certain",
      "attestations": [
        {
          "timePeriod": "hellenistic-republican",
          "timePeriodURI": "https://pleiades.stoa.org/vocabularies/time-periods/hellenistic-republican",
          "confidence": "confident",
          "confidenceURI": "https://pleiades.stoa.org/vocabularies/attestation-confidence/confident"
        },
        {
          "timePeriod": "roman",
          "timePeriodURI": "https://pleiades.stoa.org/vocabularies/time-periods/roman",
          "confidence": "confident",
          "confidenceURI": "https://pleiades.stoa.org/vocabularies/attestation-confidence/confident"
        },
        {
          "timePeriod": "late-antique",
          "timePeriodURI": "https://pleiades.stoa.org/vocabularies/time-periods/late-antique",
          "confidence": "confident",
          "confidenceURI": "https://pleiades.stoa.org/vocabularies/attestation-confidence/confident"
        }
      ],
      "references": [
        {
          "alternateURI": "",
          "accessURI": "http://francia.ahlfeldt.se/imperium.php",
          "citationDetail": "",
          "citationTypeURI": "http://purl.org/spar/cito/cites",
          "shortTitle": "",
          "bibliographicURI": "",
          "formattedCitation": "Johan \u00c5hlfeldt, Digital Atlas of the Roman Empire, 2012.",
          "otherIdentifier": " ",
          "type": "cites"
        }
      ],
      "id": "dare-location",
      "featureTypeURI": [
        "https://pleiades.stoa.org/vocabularies/place-types/settlement"
      ],
      "end": 640,
      "title": "DARE Location",
      "provenance": "Digital Atlas of the Roman Empire (2012-10-15)",
      "associationCertaintyURI": "https://pleiades.stoa.org/vocabularies/association-certainty/certain",
      "start": -330,
      "locationTypeURI": [
        "https://pleiades.stoa.org/vocabularies/place-types/settlement"
      ],
      "archaeologicalRemains": "unknown",
      "details": "",
      "review_state": "published",
      "accuracy_value": 10.0,
      "accuracy": "https://pleiades.stoa.org/features/metadata/dare-3",
      "featureType": [
        "settlement"
      ],
      "description": "Representative point location, site precision",
      "created": "2012-10-20T20:13:54Z",
      "geometry": {
        "type": "Point",
        "coordinates": [
          34.432417,
          30.87593
        ]
      },
      "locationType": [
        "representative"
      ],
      "uri": "https://pleiades.stoa.org/places/687988/dare-location",
      "creators": [
        {
          "username": "jahlfeldt",
          "homepage": null,
          "name": "Johan \u00c5hlfeldt",
          "uri": "https://pleiades.stoa.org/author/jahlfeldt"
        }
      ],
      "@type": "Location",
      "history": [
        {
          "action": "Publish externally",
          "modifiedBy": "sgillies",
          "modified": "2012-10-20T20:13:55Z"
        },
        {
          "action": "Submit for review",
          "modifiedBy": "sgillies",
          "modified": "2012-10-20T20:13:55Z"
        },
        {
          "comment": "Location updates and tags from Johan Ahlfeldt's (jahlfeldt) Digital Atlas of the Roman Empire in October 2012",
          "modifiedBy": "sgillies",
          "modified": "2012-10-20T20:13:55Z"
        },
        {
          "action": "Create",
          "modifiedBy": "sgillies",
          "modified": "2012-10-20T20:13:54Z"
        }
      ]
    }
  ],
  "connections": [],
  "references": [
    {
      "alternateURI": "",
      "accessURI": "",
      "citationDetail": "",
      "citationTypeURI": "http://purl.org/spar/cito/seeFurther",
      "shortTitle": "",
      "bibliographicURI": "http://openlibrary.org/works/OL8327792W",
      "formattedCitation": "BAtlas 70 E4 Nessana",
      "otherIdentifier": " ",
      "type": "seeFurther"
    },
    {
      "alternateURI": "",
      "accessURI": "",
      "citationDetail": "",
      "citationTypeURI": "http://purl.org/spar/cito/seeFurther",
      "shortTitle": "",
      "bibliographicURI": "http://atlantides.org/bibliography/c.html#Colt-1962",
      "formattedCitation": "Colt 1962",
      "otherIdentifier": "",
      "type": "seeFurther"
    },
    {
      "alternateURI": "",
      "accessURI": "http://www.worldcat.org/oclc/695616438",
      "citationDetail": "3 1145-49",
      "citationTypeURI": "http://purl.org/spar/cito/seeFurther",
      "shortTitle": "NEAEHL",
      "bibliographicURI": "https://www.zotero.org/groups/pleiades/items/4Q6WNJMK",
      "formattedCitation": "<div class=\"csl-entry\">S\u030ct\u0323ern, Efrayim, ed. <i>New Encyclopedia of Archaeological Excavations in the Holy Land</i>. 5 vols. Jerusalem: Simon &amp; Schuster, 1993. http://www.worldcat.org/oclc/695616438.</div>",
      "otherIdentifier": "",
      "type": "seeFurther"
    },
    {
      "alternateURI": "",
      "accessURI": "http://www.trismegistos.org/place/3162",
      "citationDetail": "",
      "citationTypeURI": "http://purl.org/spar/cito/citesAsRelated",
      "shortTitle": "",
      "bibliographicURI": "",
      "formattedCitation": "TM, GEO ID 3162",
      "otherIdentifier": " ",
      "type": "citesAsRelated"
    }
  ],
  "names": [
    {
      "nameType": "geographic",
      "transcriptionAccuracy": "accurate",
      "associationCertainty": "certain",
      "romanized": "Nessana",
      "attestations": [
        {
          "timePeriod": "hellenistic-republican",
          "timePeriodURI": "https://pleiades.stoa.org/vocabularies/time-periods/hellenistic-republican",
          "confidence": "confident",
          "confidenceURI": "https://pleiades.stoa.org/vocabularies/attestation-confidence/confident"
        },
        {
          "timePeriod": "roman",
          "timePeriodURI": "https://pleiades.stoa.org/vocabularies/time-periods/roman",
          "confidence": "confident",
          "confidenceURI": "https://pleiades.stoa.org/vocabularies/attestation-confidence/confident"
        },
        {
          "timePeriod": "late-antique",
          "timePeriodURI": "https://pleiades.stoa.org/vocabularies/time-periods/late-antique",
          "confidence": "confident",
          "confidenceURI": "https://pleiades.stoa.org/vocabularies/attestation-confidence/confident"
        }
      ],
      "references": [],
      "id": "nessana",
      "end": 640,
      "contributors": [
        {
          "username": null,
          "name": "R. Talbert"
        },
        {
          "username": null,
          "name": "T. Elliott"
        },
        {
          "username": "sgillies",
          "homepage": null,
          "name": "Sean Gillies",
          "uri": "https://pleiades.stoa.org/author/sgillies"
        }
      ],
      "provenance": "Barrington Atlas: BAtlas 70 E4 Nessana",
      "associationCertaintyURI": "https://pleiades.stoa.org/vocabularies/association-certainty/certain",
      "start": -330,
      "details": "",
      "review_state": "published",
      "description": "",
      "transcriptionCompleteness": "complete",
      "language": "",
      "created": "2009-09-17T12:33:49Z",
      "uri": "https://pleiades.stoa.org/places/687988/nessana",
      "creators": [
        {
          "username": null,
          "name": "B. Isaac"
        }
      ],
      "attested": "",
      "@type": "Name",
      "history": [
        {
          "comment": "Global migration and reindexing of citations and provenance, February 2012",
          "modifiedBy": "admin",
          "modified": "2012-02-15T07:55:44Z"
        },
        {
          "action": "Publish externally",
          "modifiedBy": "thomase",
          "modified": "2009-09-17T13:47:54Z"
        },
        {
          "action": "Submit for review",
          "modifiedBy": "sgillies",
          "modified": "2009-09-17T13:04:20Z"
        },
        {
          "action": "Create",
          "modifiedBy": "sgillies",
          "modified": "2009-09-17T12:33:49Z"
        }
      ]
    },
    {
      "nameType": "geographic",
      "transcriptionAccuracy": "accurate",
      "associationCertainty": "certain",
      "romanized": "Nizana",
      "attestations": [
        {
          "timePeriod": "hellenistic-republican",
          "timePeriodURI": "https://pleiades.stoa.org/vocabularies/time-periods/hellenistic-republican",
          "confidence": "confident",
          "confidenceURI": "https://pleiades.stoa.org/vocabularies/attestation-confidence/confident"
        },
        {
          "timePeriod": "roman",
          "timePeriodURI": "https://pleiades.stoa.org/vocabularies/time-periods/roman",
          "confidence": "confident",
          "confidenceURI": "https://pleiades.stoa.org/vocabularies/attestation-confidence/confident"
        },
        {
          "timePeriod": "late-antique",
          "timePeriodURI": "https://pleiades.stoa.org/vocabularies/time-periods/late-antique",
          "confidence": "confident",
          "confidenceURI": "https://pleiades.stoa.org/vocabularies/attestation-confidence/confident"
        }
      ],
      "references": [],
      "id": "nizana",
      "end": 640,
      "contributors": [
        {
          "username": null,
          "name": "R. Talbert"
        },
        {
          "username": null,
          "name": "T. Elliott"
        },
        {
          "username": "sgillies",
          "homepage": null,
          "name": "Sean Gillies",
          "uri": "https://pleiades.stoa.org/author/sgillies"
        }
      ],
      "provenance": "Barrington Atlas: BAtlas 70 E4 Nessana",
      "associationCertaintyURI": "https://pleiades.stoa.org/vocabularies/association-certainty/certain",
      "start": -330,
      "details": "",
      "review_state": "published",
      "description": "",
      "transcriptionCompleteness": "complete",
      "language": "",
      "created": "2009-09-17T12:33:49Z",
      "uri": "https://pleiades.stoa.org/places/687988/nizana",
      "creators": [
        {
          "username": null,
          "name": "B. Isaac"
        }
      ],
      "attested": "",
      "@type": "Name",
      "history": [
        {
          "comment": "Global migration and reindexing of citations and provenance, February 2012",
          "modifiedBy": "admin",
          "modified": "2012-02-15T07:55:44Z"
        },
        {
          "comment": "Time periods copied from sibling. See http://atlantides.org/trac/pleiades/wiki/PlaceUpgradesAndMigrations",
          "modifiedBy": "sgillies",
          "modified": "2011-01-20T03:31:06Z"
        },
        {
          "action": "Publish externally",
          "modifiedBy": "thomase",
          "modified": "2009-09-17T13:47:54Z"
        },
        {
          "action": "Submit for review",
          "modifiedBy": "sgillies",
          "modified": "2009-09-17T13:04:20Z"
        },
        {
          "action": "Create",
          "modifiedBy": "sgillies",
          "modified": "2009-09-17T12:33:49Z"
        }
      ]
    },
    {
      "nameType": "geographic",
      "transcriptionAccuracy": "accurate",
      "associationCertainty": "certain",
      "romanized": "Auja Hafir",
      "attestations": [
        {
          "timePeriod": "modern",
          "timePeriodURI": "https://pleiades.stoa.org/vocabularies/time-periods/modern",
          "confidence": "confident",
          "confidenceURI": "https://pleiades.stoa.org/vocabularies/attestation-confidence/confident"
        }
      ],
      "references": [],
      "id": "auja-hafir",
      "end": 2100,
      "contributors": [
        {
          "username": null,
          "name": "Herbert Verreth"
        },
        {
          "username": null,
          "name": "Mark Depauw"
        },
        {
          "username": null,
          "name": "Jen Thum"
        }
      ],
      "provenance": "Trismegistos",
      "associationCertaintyURI": "https://pleiades.stoa.org/vocabularies/association-certainty/certain",
      "start": 1700,
      "details": "",
      "review_state": "published",
      "description": "Modern Name",
      "transcriptionCompleteness": "complete",
      "language": "",
      "created": "2012-05-03T17:25:44Z",
      "uri": "https://pleiades.stoa.org/places/687988/auja-hafir",
      "creators": [
        {
          "username": "adamp",
          "homepage": null,
          "name": "Adam Prins",
          "uri": "https://pleiades.stoa.org/author/adamp"
        }
      ],
      "attested": "",
      "@type": "Name",
      "history": [
        {
          "action": "Publish externally",
          "modifiedBy": "sgillies",
          "modified": "2012-05-03T17:25:45Z"
        },
        {
          "action": "Submit for review",
          "modifiedBy": "sgillies",
          "modified": "2012-05-03T17:25:45Z"
        },
        {
          "comment": "Trismegistos references from Adam Prins et al (adamp, Mark Depauw, Herbert Verreth, Jen Thum) and reviewd by Tom Elliott (thomase) in May 2012",
          "modifiedBy": "sgillies",
          "modified": "2012-05-03T17:25:45Z"
        },
        {
          "action": "Create",
          "modifiedBy": "sgillies",
          "modified": "2012-05-03T17:25:44Z"
        }
      ]
    }
  ],
  "id": "687988",
  "subject": [
    "dare:ancient=1",
    "dare:feature=settlement",
    "dare:major=0"
  ],
  "title": "Nessana",
  "provenance": "Barrington Atlas: BAtlas 70 E4 Nessana",
  "placeTypeURIs": [
    "https://pleiades.stoa.org/vocabularies/place-types/settlement"
  ],
  "details": "The Barrington Atlas Directory notes: Auja el Hafir",
  "@context": {
    "snippet": "dcterms:abstract",
    "rights": "dcterms:rights",
    "description": "dcterms:description",
    "title": "dcterms:title",
    "dcterms": "http://purl.org/dc/terms/",
    "subject": "dcterms:subject",
    "uri": "@id",
    "created": "dcterms:created"
  },
  "review_state": "published",
  "type": "FeatureCollection",
  "description": "An ancient place, cited: BAtlas 70 E4 Nessana",
  "reprPoint": [
    34.427774,
    30.876260000000002
  ],
  "placeTypes": [
    "settlement"
  ],
  "bbox": [
    34.423131,
    30.87593,
    34.432417,
    30.87659
  ],
  "connectsWith": [],
  "rights": "Copyright \u00a9 The Creators. Sharing and remixing permitted under terms of the Creative Commons Attribution 3.0 License (cc-by).",
  "created": "2009-09-17T12:33:49Z",
  "uri": "https://pleiades.stoa.org/places/687988",
  "creators": [
    {
      "username": null,
      "name": "B. Isaac"
    }
  ],
  "@type": "Place",
  "history": [
    {
      "comment": "Initial revision",
      "modifiedBy": "jbecker",
      "modified": "2019-01-30T17:59:07Z"
    },
    {
      "comment": "Location updates and tags from Johan Ahlfeldt's (jahlfeldt) Digital Atlas of the Roman Empire in October 2012",
      "modifiedBy": "sgillies",
      "modified": "2012-10-20T20:13:56Z"
    },
    {
      "comment": "Trismegistos references from Adam Prins et al (adamp, Mark Depauw, Herbert Verreth, Jen Thum) and reviewd by Tom Elliott (thomase) in May 2012",
      "modifiedBy": "sgillies",
      "modified": "2012-05-03T17:25:46Z"
    },
    {
      "comment": "Global migration and reindexing of citations and provenance, February 2012",
      "modifiedBy": "admin",
      "modified": "2012-02-15T07:55:43Z"
    },
    {
      "comment": "Fixing modern/alt locations fumbled in intial import",
      "modifiedBy": "sgillies",
      "modified": "2011-12-20T21:51:53Z"
    },
    {
      "comment": "New locations, coordinates, and metadata from Harvard's DARMC project. See http://atlantides.org/trac/pleiades/wiki/PlaceUpgradesAndMigrations",
      "modifiedBy": "sgillies",
      "modified": "2011-03-09T19:34:43Z"
    },
    {
      "action": "Publish externally",
      "modifiedBy": "thomase",
      "modified": "2009-09-17T13:47:54Z"
    },
    {
      "action": "Submit for review",
      "modifiedBy": "sgillies",
      "modified": "2009-09-17T13:04:20Z"
    },
    {
      "action": "Create",
      "modifiedBy": "sgillies",
      "modified": "2009-09-17T12:33:49Z"
    }
  ]
}